fastapi_agent/__init__.py
fastapi_agent/fastapi_agent.py
fastapi_agent/fastapi_auth.py
fastapi_agent/fastapi_discovery.py
fastapi_agent/agents/__init__.py
fastapi_agent/agents/base_agent.py
fastapi_agent/agents/pydantic_ai.py
fastapi_agent/chat_ui/index.html
fastapi_agent/chat_ui/script.js
fastapi_agent/chat_ui/styles.css
fastapi_agent-0.2.7.dist-info/METADATA
fastapi_agent-0.2.7.dist-info/WHEEL
fastapi_agent-0.2.7.dist-info/licenses/LICENSE
fastapi_agent-0.2.7.dist-info/RECORD
