Metadata-Version: 2.4
Name: fastapi-agent
Version: 0.2.7
Summary: Add an AI Agent to your FastAPI application. The agent knows how to interact with your endpoints within a chat interface.
Project-URL: Homepage, https://github.com/orco82/fastapi-agent
Project-URL: Repository, https://github.com/orco82/fastapi-agent
Project-URL: Documentation, https://github.com/orco82/fastapi-agent#readme
Project-URL: Bug Tracker, https://github.com/orco82/fastapi-agent/issues
Author-email: Or Cohen <orco82@gmail.com>
License: MIT
License-File: LICENSE
Keywords: agent,ai,api,chat,fastapi
Classifier: Development Status :: 3 - Alpha
Classifier: Framework :: FastAPI
Classifier: Framework :: Pydantic
Classifier: Intended Audience :: Developers
Classifier: License :: OSI Approved :: MIT License
Classifier: Operating System :: OS Independent
Classifier: Programming Language :: Python
Classifier: Programming Language :: Python :: 3
Classifier: Programming Language :: Python :: 3.10
Classifier: Programming Language :: Python :: 3.11
Classifier: Programming Language :: Python :: 3.12
Classifier: Programming Language :: Python :: 3.13
Requires-Python: >=3.10
Requires-Dist: fastapi>=0.116.1
Requires-Dist: httpx>=0.28.1
Requires-Dist: pydantic-ai>=0.4.7
Requires-Dist: pydantic>=2.11.7
Requires-Dist: uvicorn>=0.35.0
